dmgeometry/__init__.py
dmgeometry/circle.py
dmgeometry/rectangle.py
dmgeometry-0.4.dist-info/METADATA
dmgeometry-0.4.dist-info/WHEEL
dmgeometry-0.4.dist-info/top_level.txt
dmgeometry-0.4.dist-info/RECORD
