Metadata-Version: 2.1
Name: dmgeometry
Version: 0.4
Summary: A simple Python library for calculating the area of geometric shapes.
Author: murali
